multipoly.py
multipoly-0.9.3.dist-info/LICENSE
multipoly-0.9.3.dist-info/METADATA
multipoly-0.9.3.dist-info/WHEEL
multipoly-0.9.3.dist-info/top_level.txt
multipoly-0.9.3.dist-info/RECORD
